<?xml version="1.0" encoding="utf-8"?>
<RESULTS version="Quant-UR B.1.1.0  Reseach Use Only">
   <SAMPLE date="19-Dec-2014 23:30:56" name="ALZ_Urine_Rack04_RCM_191214_expno310.100000.10r" project="" type="urine"/>
   <CLASSIFICATION/>
   <VERIFICATION/>
   <QUANTIFICATION version="Quant-UR B.1.1.0  Reseach Use Only">
      <PARAMETER name="Creatinine" type="quantification">
         <VALUE conc="5.9" concUnit="mmol/L" lod="0.3" lodUnit="mmol/L" loq="-" loqUnit="mmol/L"/>
         <RELDATA errConc="0.062" errConcUnit="mmol/L" rawConc="5.866" rawConcUnit="mmol/L" sigCorr="100" sigCorrUnit="%"/>
         <REFERENCE source="NMR Database" unit="mmol/L" vmax="19" vmin="1"/>
      </PARAMETER>
      <PARAMETER name="Dimethylamine" type="quantification">
         <VALUE conc="0" concUnit="mmol/L" lod="0.183" lodUnit="mmol/L" loq="-" loqUnit="mmol/L"/>
         <VALUERELATIVE conc="0" concUnit="mmol/mol Crea" lod="31" lodUnit="mmol/mol Crea" loq="-" loqUnit="mmol/mol Crea"/>
         <RELDATA errConc="0.003" errConcUnit="mmol/L" rawConc="0.176" rawConcUnit="mmol/L" sigCorr="100" sigCorrUnit="%"/>
         <REFERENCE source="NMR Database" unit="mmol/mol Crea" vmax="54" vmin="-"/>
      </PARAMETER>
      <PARAMETER name="Trimethylamine" type="quantification">
         <VALUE conc="0" concUnit="mmol/L" lod="0.012" lodUnit="mmol/L" loq="-" loqUnit="mmol/L"/>
         <VALUERELATIVE conc="0" concUnit="mmol/mol Crea" lod="2" lodUnit="mmol/mol Crea" loq="-" loqUnit="mmol/mol Crea"/>
         <RELDATA errConc="0.002" errConcUnit="mmol/L" rawConc="0.003" rawConcUnit="mmol/L" sigCorr="23" sigCorrUnit="%"/>
         <REFERENCE source="NMR Database" unit="mmol/mol Crea" vmax="3" vmin="-"/>
      </PARAMETER>
      <PARAMETER name="1-Methylhistidine" type="quantification">
         <VALUE conc="0" concUnit="mmol/L" lod="0.088" lodUnit="mmol/L" loq="-" loqUnit="mmol/L"/>
         <VALUERELATIVE conc="0" concUnit="mmol/mol Crea" lod="15" lodUnit="mmol/mol Crea" loq="-" loqUnit="mmol/mol Crea"/>
         <RELDATA errConc="0.044" errConcUnit="mmol/L" rawConc="0.000" rawConcUnit="mmol/L" sigCorr="0" sigCorrUnit="%"/>
         <REFERENCE source="NMR Database" unit="mmol/mol Crea" vmax="15" vmin="-"/>
      </PARAMETER>
      <PARAMETER name="2-Furoylglycine" type="quantification">
         <VALUE conc="0" concUnit="mmol/L" lod="0.230" lodUnit="mmol/L" loq="-" loqUnit="mmol/L"/>
         <VALUERELATIVE conc="0" concUnit="mmol/mol Crea" lod="39" lodUnit="mmol/mol Crea" loq="-" loqUnit="mmol/mol Crea"/>
         <RELDATA errConc="0.009" errConcUnit="mmol/L" rawConc="0.134" rawConcUnit="mmol/L" sigCorr="99" sigCorrUnit="%"/>
         <REFERENCE source="NMR Database" unit="mmol/mol Crea" vmax="40" vmin="-"/>
      </PARAMETER>
      <PARAMETER name="4-Aminobutyric acid" type="quantification">
         <VALUE conc="0" concUnit="mmol/L" lod="0.118" lodUnit="mmol/L" loq="-" loqUnit="mmol/L"/>
         <VALUERELATIVE conc="0" concUnit="mmol/mol Crea" lod="20" lodUnit="mmol/mol Crea" loq="-" loqUnit="mmol/mol Crea"/>
         <RELDATA errConc="0.238" errConcUnit="mmol/L" rawConc="0.000" rawConcUnit="mmol/L" sigCorr="0" sigCorrUnit="%"/>
         <REFERENCE source="NMR Database" unit="mmol/mol Crea" vmax="20" vmin="-"/>
      </PARAMETER>
      <PARAMETER name="Alanine" type="quantification">
         <VALUE conc="0.16" concUnit="mmol/L" lod="0.059" lodUnit="mmol/L" loq="-" loqUnit="mmol/L"/>
         <VALUERELATIVE conc="27" concUnit="mmol/mol Crea" lod="10" lodUnit="mmol/mol Crea" loq="-" loqUnit="mmol/mol Crea"/>
         <RELDATA errConc="0.011" errConcUnit="mmol/L" rawConc="0.160" rawConcUnit="mmol/L" sigCorr="100" sigCorrUnit="%"/>
         <REFERENCE source="NMR Database" unit="mmol/mol Crea" vmax="72" vmin="11"/>
      </PARAMETER>
      <PARAMETER name="Arginine" type="quantification">
         <VALUE conc="0" concUnit="mmol/L" lod="4.425" lodUnit="mmol/L" loq="-" loqUnit="mmol/L"/>
         <VALUERELATIVE conc="0" concUnit="mmol/mol Crea" lod="750" lodUnit="mmol/mol Crea" loq="-" loqUnit="mmol/mol Crea"/>
         <RELDATA errConc="0.750" errConcUnit="mmol/L" rawConc="0.463" rawConcUnit="mmol/L" sigCorr="2" sigCorrUnit="%"/>
         <REFERENCE source="NMR Database" unit="mmol/mol Crea" vmax="750" vmin="-"/>
      </PARAMETER>
      <PARAMETER name="Betaine" type="quantification">
         <VALUE conc="0.11" concUnit="mmol/L" lod="0.041" lodUnit="mmol/L" loq="-" loqUnit="mmol/L"/>
         <VALUERELATIVE conc="19" concUnit="mmol/mol Crea" lod="7" lodUnit="mmol/mol Crea" loq="-" loqUnit="mmol/mol Crea"/>
         <RELDATA errConc="0.023" errConcUnit="mmol/L" rawConc="0.110" rawConcUnit="mmol/L" sigCorr="100" sigCorrUnit="%"/>
         <REFERENCE source="NMR Database" unit="mmol/mol Crea" vmax="78" vmin="9"/>
      </PARAMETER>
      <PARAMETER name="Creatine" type="quantification">
         <VALUE conc="0" concUnit="mmol/L" lod="0.295" lodUnit="mmol/L" loq="-" loqUnit="mmol/L"/>
         <VALUERELATIVE conc="0" concUnit="mmol/mol Crea" lod="50" lodUnit="mmol/mol Crea" loq="-" loqUnit="mmol/mol Crea"/>
         <RELDATA errConc="0.062" errConcUnit="mmol/L" rawConc="0.142" rawConcUnit="mmol/L" sigCorr="100" sigCorrUnit="%"/>
         <REFERENCE source="NMR Database" unit="mmol/mol Crea" vmax="280" vmin="-"/>
      </PARAMETER>
      <PARAMETER name="Glycine" type="quantification">
         <VALUE conc="0.74" concUnit="mmol/L" lod="0.201" lodUnit="mmol/L" loq="-" loqUnit="mmol/L"/>
         <VALUERELATIVE conc="130" concUnit="mmol/mol Crea" lod="34" lodUnit="mmol/mol Crea" loq="-" loqUnit="mmol/mol Crea"/>
         <RELDATA errConc="0.019" errConcUnit="mmol/L" rawConc="0.741" rawConcUnit="mmol/L" sigCorr="100" sigCorrUnit="%"/>
         <REFERENCE source="NMR Database" unit="mmol/mol Crea" vmax="440" vmin="38"/>
      </PARAMETER>
      <PARAMETER name="Guanidinoacetic acid" type="quantification">
         <VALUE conc="0" concUnit="mmol/L" lod="0.590" lodUnit="mmol/L" loq="-" loqUnit="mmol/L"/>
         <VALUERELATIVE conc="0" concUnit="mmol/mol Crea" lod="100" lodUnit="mmol/mol Crea" loq="-" loqUnit="mmol/mol Crea"/>
         <RELDATA errConc="0.137" errConcUnit="mmol/L" rawConc="0.345" rawConcUnit="mmol/L" sigCorr="88" sigCorrUnit="%"/>
         <REFERENCE source="NMR Database" unit="mmol/mol Crea" vmax="140" vmin="-"/>
      </PARAMETER>
      <PARAMETER name="Methionine" type="quantification">
         <VALUE conc="0" concUnit="mmol/L" lod="0.106" lodUnit="mmol/L" loq="-" loqUnit="mmol/L"/>
         <VALUERELATIVE conc="0" concUnit="mmol/mol Crea" lod="18" lodUnit="mmol/mol Crea" loq="-" loqUnit="mmol/mol Crea"/>
         <RELDATA errConc="0.463" errConcUnit="mmol/L" rawConc="0.000" rawConcUnit="mmol/L" sigCorr="0" sigCorrUnit="%"/>
         <REFERENCE source="NMR Database" unit="mmol/mol Crea" vmax="18" vmin="-"/>
      </PARAMETER>
      <PARAMETER name="N,N-Dimethylglycine" type="quantification">
         <VALUE conc="0.04" concUnit="mmol/L" lod="0.029" lodUnit="mmol/L" loq="-" loqUnit="mmol/L"/>
         <VALUERELATIVE conc="6" concUnit="mmol/mol Crea" lod="5" lodUnit="mmol/mol Crea" loq="-" loqUnit="mmol/mol Crea"/>
         <RELDATA errConc="0.017" errConcUnit="mmol/L" rawConc="0.036" rawConcUnit="mmol/L" sigCorr="75" sigCorrUnit="%"/>
         <REFERENCE source="NMR Database" unit="mmol/mol Crea" vmax="15" vmin="-"/>
      </PARAMETER>
      <PARAMETER name="Sarcosine" type="quantification">
         <VALUE conc="0" concUnit="mmol/L" lod="0.012" lodUnit="mmol/L" loq="-" loqUnit="mmol/L"/>
         <VALUERELATIVE conc="0" concUnit="mmol/mol Crea" lod="2" lodUnit="mmol/mol Crea" loq="-" loqUnit="mmol/mol Crea"/>
         <RELDATA errConc="0.004" errConcUnit="mmol/L" rawConc="0.000" rawConcUnit="mmol/L" sigCorr="0" sigCorrUnit="%"/>
         <REFERENCE source="NMR Database" unit="mmol/mol Crea" vmax="7" vmin="-"/>
      </PARAMETER>
      <PARAMETER name="Taurine" type="quantification">
         <VALUE conc="0" concUnit="mmol/L" lod="0.826" lodUnit="mmol/L" loq="-" loqUnit="mmol/L"/>
         <VALUERELATIVE conc="0" concUnit="mmol/mol Crea" lod="140" lodUnit="mmol/mol Crea" loq="-" loqUnit="mmol/mol Crea"/>
         <RELDATA errConc="0.156" errConcUnit="mmol/L" rawConc="0.406" rawConcUnit="mmol/L" sigCorr="95" sigCorrUnit="%"/>
         <REFERENCE source="NMR Database" unit="mmol/mol Crea" vmax="170" vmin="-"/>
      </PARAMETER>
      <PARAMETER name="Valine" type="quantification">
         <VALUE conc="0.02" concUnit="mmol/L" lod="0.012" lodUnit="mmol/L" loq="-" loqUnit="mmol/L"/>
         <VALUERELATIVE conc="4" concUnit="mmol/mol Crea" lod="2" lodUnit="mmol/mol Crea" loq="-" loqUnit="mmol/mol Crea"/>
         <RELDATA errConc="0.013" errConcUnit="mmol/L" rawConc="0.024" rawConcUnit="mmol/L" sigCorr="69" sigCorrUnit="%"/>
         <REFERENCE source="NMR Database" unit="mmol/mol Crea" vmax="7" vmin="-"/>
      </PARAMETER>
      <PARAMETER name="Benzoic acid" type="quantification">
         <VALUE conc="0" concUnit="mmol/L" lod="0.059" lodUnit="mmol/L" loq="-" loqUnit="mmol/L"/>
         <VALUERELATIVE conc="0" concUnit="mmol/mol Crea" lod="10" lodUnit="mmol/mol Crea" loq="-" loqUnit="mmol/mol Crea"/>
         <RELDATA errConc="0.031" errConcUnit="mmol/L" rawConc="0.000" rawConcUnit="mmol/L" sigCorr="0" sigCorrUnit="%"/>
         <REFERENCE source="NMR Database" unit="mmol/mol Crea" vmax="10" vmin="-"/>
      </PARAMETER>
      <PARAMETER name="D-Mandelic acid" type="quantification">
         <VALUE conc="0" concUnit="mmol/L" lod="0.012" lodUnit="mmol/L" loq="-" loqUnit="mmol/L"/>
         <VALUERELATIVE conc="0" concUnit="mmol/mol Crea" lod="2" lodUnit="mmol/mol Crea" loq="-" loqUnit="mmol/mol Crea"/>
         <RELDATA errConc="0.080" errConcUnit="mmol/L" rawConc="0.000" rawConcUnit="mmol/L" sigCorr="0" sigCorrUnit="%"/>
         <REFERENCE source="NMR Database" unit="mmol/mol Crea" vmax="17" vmin="2"/>
      </PARAMETER>
      <PARAMETER name="Hippuric acid" type="quantification">
         <VALUE conc="1.2" concUnit="mmol/L" lod="1.003" lodUnit="mmol/L" loq="-" loqUnit="mmol/L"/>
         <VALUERELATIVE conc="200" concUnit="mmol/mol Crea" lod="170" lodUnit="mmol/mol Crea" loq="-" loqUnit="mmol/mol Crea"/>
         <RELDATA errConc="0.124" errConcUnit="mmol/L" rawConc="1.186" rawConcUnit="mmol/L" sigCorr="99" sigCorrUnit="%"/>
         <REFERENCE source="NMR Database" unit="mmol/mol Crea" vmax="660" vmin="-"/>
      </PARAMETER>
      <PARAMETER name="Acetic acid" type="quantification">
         <VALUE conc="0.08" concUnit="mmol/L" lod="0.029" lodUnit="mmol/L" loq="-" loqUnit="mmol/L"/>
         <VALUERELATIVE conc="13" concUnit="mmol/mol Crea" lod="5" lodUnit="mmol/mol Crea" loq="-" loqUnit="mmol/mol Crea"/>
         <RELDATA errConc="0.010" errConcUnit="mmol/L" rawConc="0.076" rawConcUnit="mmol/L" sigCorr="98" sigCorrUnit="%"/>
         <REFERENCE source="NMR Database" unit="mmol/mol Crea" vmax="51" vmin="-"/>
      </PARAMETER>
      <PARAMETER name="Citric acid" type="quantification">
         <VALUE conc="1.9" concUnit="mmol/L" lod="0.236" lodUnit="mmol/L" loq="-" loqUnit="mmol/L"/>
         <VALUERELATIVE conc="320" concUnit="mmol/mol Crea" lod="40" lodUnit="mmol/mol Crea" loq="-" loqUnit="mmol/mol Crea"/>
         <RELDATA errConc="0.118" errConcUnit="mmol/L" rawConc="1.850" rawConcUnit="mmol/L" sigCorr="100" sigCorrUnit="%"/>
         <REFERENCE source="NMR Database" unit="mmol/mol Crea" vmax="700" vmin="-"/>
      </PARAMETER>
      <PARAMETER name="Formic acid" type="quantification">
         <VALUE conc="0.11" concUnit="mmol/L" lod="0.059" lodUnit="mmol/L" loq="-" loqUnit="mmol/L"/>
         <VALUERELATIVE conc="19" concUnit="mmol/mol Crea" lod="10" lodUnit="mmol/mol Crea" loq="-" loqUnit="mmol/mol Crea"/>
         <RELDATA errConc="0.005" errConcUnit="mmol/L" rawConc="0.113" rawConcUnit="mmol/L" sigCorr="100" sigCorrUnit="%"/>
         <REFERENCE source="NMR Database" unit="mmol/mol Crea" vmax="43" vmin="-"/>
      </PARAMETER>
      <PARAMETER name="Fumaric acid" type="quantification">
         <VALUE conc="0" concUnit="mmol/L" lod="0.012" lodUnit="mmol/L" loq="-" loqUnit="mmol/L"/>
         <VALUERELATIVE conc="0" concUnit="mmol/mol Crea" lod="2" lodUnit="mmol/mol Crea" loq="-" loqUnit="mmol/mol Crea"/>
         <RELDATA errConc="0.001" errConcUnit="mmol/L" rawConc="0.003" rawConcUnit="mmol/L" sigCorr="73" sigCorrUnit="%"/>
         <REFERENCE source="NMR Database" unit="mmol/mol Crea" vmax="3" vmin="-"/>
      </PARAMETER>
      <PARAMETER name="Imidazole" type="quantification">
         <VALUE conc="0" concUnit="mmol/L" lod="0.283" lodUnit="mmol/L" loq="-" loqUnit="mmol/L"/>
         <VALUERELATIVE conc="0" concUnit="mmol/mol Crea" lod="48" lodUnit="mmol/mol Crea" loq="-" loqUnit="mmol/mol Crea"/>
         <RELDATA errConc="0.035" errConcUnit="mmol/L" rawConc="0.030" rawConcUnit="mmol/L" sigCorr="43" sigCorrUnit="%"/>
         <REFERENCE source="NMR Database" unit="mmol/mol Crea" vmax="48" vmin="-"/>
      </PARAMETER>
      <PARAMETER name="Lactic acid" type="quantification">
         <VALUE conc="0" concUnit="mmol/L" lod="0.289" lodUnit="mmol/L" loq="-" loqUnit="mmol/L"/>
         <VALUERELATIVE conc="0" concUnit="mmol/mol Crea" lod="49" lodUnit="mmol/mol Crea" loq="-" loqUnit="mmol/mol Crea"/>
         <RELDATA errConc="0.052" errConcUnit="mmol/L" rawConc="0.135" rawConcUnit="mmol/L" sigCorr="99" sigCorrUnit="%"/>
         <REFERENCE source="NMR Database" unit="mmol/mol Crea" vmax="110" vmin="-"/>
      </PARAMETER>
      <PARAMETER name="Proline betaine" type="quantification">
         <VALUE conc="0.28" concUnit="mmol/L" lod="0.147" lodUnit="mmol/L" loq="-" loqUnit="mmol/L"/>
         <VALUERELATIVE conc="47" concUnit="mmol/mol Crea" lod="25" lodUnit="mmol/mol Crea" loq="-" loqUnit="mmol/mol Crea"/>
         <RELDATA errConc="0.024" errConcUnit="mmol/L" rawConc="0.277" rawConcUnit="mmol/L" sigCorr="99" sigCorrUnit="%"/>
         <REFERENCE source="NMR Database" unit="mmol/mol Crea" vmax="280" vmin="-"/>
      </PARAMETER>
      <PARAMETER name="Succinic acid" type="quantification">
         <VALUE conc="0.11" concUnit="mmol/L" lod="0.029" lodUnit="mmol/L" loq="-" loqUnit="mmol/L"/>
         <VALUERELATIVE conc="19" concUnit="mmol/mol Crea" lod="5" lodUnit="mmol/mol Crea" loq="-" loqUnit="mmol/mol Crea"/>
         <RELDATA errConc="0.019" errConcUnit="mmol/L" rawConc="0.111" rawConcUnit="mmol/L" sigCorr="96" sigCorrUnit="%"/>
         <REFERENCE source="NMR Database" unit="mmol/mol Crea" vmax="39" vmin="-"/>
      </PARAMETER>
      <PARAMETER name="Tartaric acid" type="quantification">
         <VALUE conc="0.06" concUnit="mmol/L" lod="0.029" lodUnit="mmol/L" loq="-" loqUnit="mmol/L"/>
         <VALUERELATIVE conc="10" concUnit="mmol/mol Crea" lod="5" lodUnit="mmol/mol Crea" loq="-" loqUnit="mmol/mol Crea"/>
         <RELDATA errConc="0.012" errConcUnit="mmol/L" rawConc="0.060" rawConcUnit="mmol/L" sigCorr="98" sigCorrUnit="%"/>
         <REFERENCE source="NMR Database" unit="mmol/mol Crea" vmax="110" vmin="-"/>
      </PARAMETER>
      <PARAMETER name="Trigonelline" type="quantification">
         <VALUE conc="0" concUnit="mmol/L" lod="0.206" lodUnit="mmol/L" loq="-" loqUnit="mmol/L"/>
         <VALUERELATIVE conc="0" concUnit="mmol/mol Crea" lod="35" lodUnit="mmol/mol Crea" loq="-" loqUnit="mmol/mol Crea"/>
         <RELDATA errConc="0.004" errConcUnit="mmol/L" rawConc="0.137" rawConcUnit="mmol/L" sigCorr="100" sigCorrUnit="%"/>
         <REFERENCE source="NMR Database" unit="mmol/mol Crea" vmax="67" vmin="-"/>
      </PARAMETER>
      <PARAMETER name="2-Methylsuccinic acid" type="quantification">
         <VALUE conc="0" concUnit="mmol/L" lod="0.283" lodUnit="mmol/L" loq="-" loqUnit="mmol/L"/>
         <VALUERELATIVE conc="0" concUnit="mmol/mol Crea" lod="48" lodUnit="mmol/mol Crea" loq="-" loqUnit="mmol/mol Crea"/>
         <RELDATA errConc="0.208" errConcUnit="mmol/L" rawConc="0.000" rawConcUnit="mmol/L" sigCorr="0" sigCorrUnit="%"/>
         <REFERENCE source="NMR Database" unit="mmol/mol Crea" vmax="48" vmin="-"/>
      </PARAMETER>
      <PARAMETER name="2-Oxoglutaric acid" type="quantification">
         <VALUE conc="0" concUnit="mmol/L" lod="0.543" lodUnit="mmol/L" loq="-" loqUnit="mmol/L"/>
         <VALUERELATIVE conc="0" concUnit="mmol/mol Crea" lod="92" lodUnit="mmol/mol Crea" loq="-" loqUnit="mmol/mol Crea"/>
         <RELDATA errConc="0.172" errConcUnit="mmol/L" rawConc="0.081" rawConcUnit="mmol/L" sigCorr="64" sigCorrUnit="%"/>
         <REFERENCE source="NMR Database" unit="mmol/mol Crea" vmax="92" vmin="-"/>
      </PARAMETER>
      <PARAMETER name="3-Hydroxybutyric acid" type="quantification">
         <VALUE conc="0" concUnit="mmol/L" lod="0.590" lodUnit="mmol/L" loq="-" loqUnit="mmol/L"/>
         <VALUERELATIVE conc="0" concUnit="mmol/mol Crea" lod="100" lodUnit="mmol/mol Crea" loq="-" loqUnit="mmol/mol Crea"/>
         <RELDATA errConc="0.555" errConcUnit="mmol/L" rawConc="0.000" rawConcUnit="mmol/L" sigCorr="0" sigCorrUnit="%"/>
         <REFERENCE source="NMR Database" unit="mmol/mol Crea" vmax="100" vmin="-"/>
      </PARAMETER>
      <PARAMETER name="Acetoacetic acid" type="quantification">
         <VALUE conc="0" concUnit="mmol/L" lod="0.083" lodUnit="mmol/L" loq="-" loqUnit="mmol/L"/>
         <VALUERELATIVE conc="0" concUnit="mmol/mol Crea" lod="14" lodUnit="mmol/mol Crea" loq="-" loqUnit="mmol/mol Crea"/>
         <RELDATA errConc="0.038" errConcUnit="mmol/L" rawConc="0.074" rawConcUnit="mmol/L" sigCorr="87" sigCorrUnit="%"/>
         <REFERENCE source="NMR Database" unit="mmol/mol Crea" vmax="30" vmin="-"/>
      </PARAMETER>
      <PARAMETER name="Acetone" type="quantification">
         <VALUE conc="0.02" concUnit="mmol/L" lod="0.012" lodUnit="mmol/L" loq="-" loqUnit="mmol/L"/>
         <VALUERELATIVE conc="4" concUnit="mmol/mol Crea" lod="2" lodUnit="mmol/mol Crea" loq="-" loqUnit="mmol/mol Crea"/>
         <RELDATA errConc="0.002" errConcUnit="mmol/L" rawConc="0.022" rawConcUnit="mmol/L" sigCorr="100" sigCorrUnit="%"/>
         <REFERENCE source="NMR Database" unit="mmol/mol Crea" vmax="7" vmin="-"/>
      </PARAMETER>
      <PARAMETER name="Oxaloacetic acid" type="quantification">
         <VALUE conc="0" concUnit="mmol/L" lod="0.100" lodUnit="mmol/L" loq="-" loqUnit="mmol/L"/>
         <VALUERELATIVE conc="0" concUnit="mmol/mol Crea" lod="17" lodUnit="mmol/mol Crea" loq="-" loqUnit="mmol/mol Crea"/>
         <RELDATA errConc="0.088" errConcUnit="mmol/L" rawConc="0.084" rawConcUnit="mmol/L" sigCorr="73" sigCorrUnit="%"/>
         <REFERENCE source="NMR Database" unit="mmol/mol Crea" vmax="66" vmin="-"/>
      </PARAMETER>
      <PARAMETER name="Pyruvic acid" type="quantification">
         <VALUE conc="0" concUnit="mmol/L" lod="0.053" lodUnit="mmol/L" loq="-" loqUnit="mmol/L"/>
         <VALUERELATIVE conc="0" concUnit="mmol/mol Crea" lod="9" lodUnit="mmol/mol Crea" loq="-" loqUnit="mmol/mol Crea"/>
         <RELDATA errConc="0.007" errConcUnit="mmol/L" rawConc="0.035" rawConcUnit="mmol/L" sigCorr="95" sigCorrUnit="%"/>
         <REFERENCE source="NMR Database" unit="mmol/mol Crea" vmax="13" vmin="-"/>
      </PARAMETER>
      <PARAMETER name="1-Methyladenosine" type="quantification">
         <VALUE conc="0" concUnit="mmol/L" lod="0.029" lodUnit="mmol/L" loq="-" loqUnit="mmol/L"/>
         <VALUERELATIVE conc="0" concUnit="mmol/mol Crea" lod="5" lodUnit="mmol/mol Crea" loq="-" loqUnit="mmol/mol Crea"/>
         <RELDATA errConc="0.122" errConcUnit="mmol/L" rawConc="0.000" rawConcUnit="mmol/L" sigCorr="0" sigCorrUnit="%"/>
         <REFERENCE source="NMR Database" unit="mmol/mol Crea" vmax="5" vmin="-"/>
      </PARAMETER>
      <PARAMETER name="1-Methylnicotinamide" type="quantification">
         <VALUE conc="0" concUnit="mmol/L" lod="0.189" lodUnit="mmol/L" loq="-" loqUnit="mmol/L"/>
         <VALUERELATIVE conc="0" concUnit="mmol/mol Crea" lod="32" lodUnit="mmol/mol Crea" loq="-" loqUnit="mmol/mol Crea"/>
         <RELDATA errConc="0.012" errConcUnit="mmol/L" rawConc="0.057" rawConcUnit="mmol/L" sigCorr="98" sigCorrUnit="%"/>
         <REFERENCE source="NMR Database" unit="mmol/mol Crea" vmax="32" vmin="-"/>
      </PARAMETER>
      <PARAMETER name="Adenosine" type="quantification">
         <VALUE conc="0" concUnit="mmol/L" lod="2.301" lodUnit="mmol/L" loq="-" loqUnit="mmol/L"/>
         <VALUERELATIVE conc="0" concUnit="mmol/mol Crea" lod="390" lodUnit="mmol/mol Crea" loq="-" loqUnit="mmol/mol Crea"/>
         <RELDATA errConc="1.016" errConcUnit="mmol/L" rawConc="0.000" rawConcUnit="mmol/L" sigCorr="0" sigCorrUnit="%"/>
         <REFERENCE source="NMR Database" unit="mmol/mol Crea" vmax="390" vmin="-"/>
      </PARAMETER>
      <PARAMETER name="Allantoin" type="quantification">
         <VALUE conc="0" concUnit="mmol/L" lod="0.100" lodUnit="mmol/L" loq="-" loqUnit="mmol/L"/>
         <VALUERELATIVE conc="0" concUnit="mmol/mol Crea" lod="17" lodUnit="mmol/mol Crea" loq="-" loqUnit="mmol/mol Crea"/>
         <RELDATA errConc="0.003" errConcUnit="mmol/L" rawConc="0.066" rawConcUnit="mmol/L" sigCorr="100" sigCorrUnit="%"/>
         <REFERENCE source="NMR Database" unit="mmol/mol Crea" vmax="47" vmin="-"/>
      </PARAMETER>
      <PARAMETER name="Allopurinol" type="quantification">
         <VALUE conc="0" concUnit="mmol/L" lod="0.059" lodUnit="mmol/L" loq="-" loqUnit="mmol/L"/>
         <VALUERELATIVE conc="0" concUnit="mmol/mol Crea" lod="10" lodUnit="mmol/mol Crea" loq="-" loqUnit="mmol/mol Crea"/>
         <RELDATA errConc="0.050" errConcUnit="mmol/L" rawConc="0.035" rawConcUnit="mmol/L" sigCorr="97" sigCorrUnit="%"/>
         <REFERENCE source="NMR Database" unit="mmol/mol Crea" vmax="11" vmin="-"/>
      </PARAMETER>
      <PARAMETER name="Caffeine" type="quantification">
         <VALUE conc="0" concUnit="mmol/L" lod="0.266" lodUnit="mmol/L" loq="-" loqUnit="mmol/L"/>
         <VALUERELATIVE conc="0" concUnit="mmol/mol Crea" lod="45" lodUnit="mmol/mol Crea" loq="-" loqUnit="mmol/mol Crea"/>
         <RELDATA errConc="0.120" errConcUnit="mmol/L" rawConc="0.117" rawConcUnit="mmol/L" sigCorr="90" sigCorrUnit="%"/>
         <REFERENCE source="NMR Database" unit="mmol/mol Crea" vmax="61" vmin="-"/>
      </PARAMETER>
      <PARAMETER name="Inosine" type="quantification">
         <VALUE conc="0" concUnit="mmol/L" lod="0.112" lodUnit="mmol/L" loq="-" loqUnit="mmol/L"/>
         <VALUERELATIVE conc="0" concUnit="mmol/mol Crea" lod="19" lodUnit="mmol/mol Crea" loq="-" loqUnit="mmol/mol Crea"/>
         <RELDATA errConc="0.053" errConcUnit="mmol/L" rawConc="0.012" rawConcUnit="mmol/L" sigCorr="95" sigCorrUnit="%"/>
         <REFERENCE source="NMR Database" unit="mmol/mol Crea" vmax="19" vmin="-"/>
      </PARAMETER>
      <PARAMETER name="D-Galactose" type="quantification">
         <VALUE conc="0" concUnit="mmol/L" lod="0.254" lodUnit="mmol/L" loq="-" loqUnit="mmol/L"/>
         <VALUERELATIVE conc="0" concUnit="mmol/mol Crea" lod="43" lodUnit="mmol/mol Crea" loq="-" loqUnit="mmol/mol Crea"/>
         <RELDATA errConc="0.002" errConcUnit="mmol/L" rawConc="0.040" rawConcUnit="mmol/L" sigCorr="96" sigCorrUnit="%"/>
         <REFERENCE source="NMR Database" unit="mmol/mol Crea" vmax="44" vmin="-"/>
      </PARAMETER>
      <PARAMETER name="D-Glucose" type="quantification">
         <VALUE conc="0.21" concUnit="mmol/L" lod="0.201" lodUnit="mmol/L" loq="-" loqUnit="mmol/L"/>
         <VALUERELATIVE conc="36" concUnit="mmol/mol Crea" lod="34" lodUnit="mmol/mol Crea" loq="-" loqUnit="mmol/mol Crea"/>
         <RELDATA errConc="0.048" errConcUnit="mmol/L" rawConc="0.211" rawConcUnit="mmol/L" sigCorr="88" sigCorrUnit="%"/>
         <REFERENCE source="NMR Database" unit="mmol/mol Crea" vmax="140" vmin="-"/>
      </PARAMETER>
      <PARAMETER name="D-Lactose" type="quantification">
         <VALUE conc="0" concUnit="mmol/L" lod="0.566" lodUnit="mmol/L" loq="-" loqUnit="mmol/L"/>
         <VALUERELATIVE conc="0" concUnit="mmol/mol Crea" lod="96" lodUnit="mmol/mol Crea" loq="-" loqUnit="mmol/mol Crea"/>
         <RELDATA errConc="0.074" errConcUnit="mmol/L" rawConc="0.166" rawConcUnit="mmol/L" sigCorr="88" sigCorrUnit="%"/>
         <REFERENCE source="NMR Database" unit="mmol/mol Crea" vmax="96" vmin="-"/>
      </PARAMETER>
      <PARAMETER name="D-Mannitol" type="quantification">
         <VALUE conc="0" concUnit="mmol/L" lod="1.062" lodUnit="mmol/L" loq="-" loqUnit="mmol/L"/>
         <VALUERELATIVE conc="0" concUnit="mmol/mol Crea" lod="180" lodUnit="mmol/mol Crea" loq="-" loqUnit="mmol/mol Crea"/>
         <RELDATA errConc="2.040" errConcUnit="mmol/L" rawConc="0.000" rawConcUnit="mmol/L" sigCorr="0" sigCorrUnit="%"/>
         <REFERENCE source="NMR Database" unit="mmol/mol Crea" vmax="180" vmin="-"/>
      </PARAMETER>
      <PARAMETER name="D-Mannose" type="quantification">
         <VALUE conc="0" concUnit="mmol/L" lod="0.035" lodUnit="mmol/L" loq="-" loqUnit="mmol/L"/>
         <VALUERELATIVE conc="0" concUnit="mmol/mol Crea" lod="6" lodUnit="mmol/mol Crea" loq="-" loqUnit="mmol/mol Crea"/>
         <RELDATA errConc="0.060" errConcUnit="mmol/L" rawConc="0.000" rawConcUnit="mmol/L" sigCorr="0" sigCorrUnit="%"/>
         <REFERENCE source="NMR Database" unit="mmol/mol Crea" vmax="8" vmin="-"/>
      </PARAMETER>
      <PARAMETER name="Myo-Inositol" type="quantification">
         <VALUE conc="0" concUnit="mmol/L" lod="25.960" lodUnit="mmol/L" loq="-" loqUnit="mmol/L"/>
         <VALUERELATIVE conc="0" concUnit="mmol/mol Crea" lod="4400" lodUnit="mmol/mol Crea" loq="-" loqUnit="mmol/mol Crea"/>
         <RELDATA errConc="5.508" errConcUnit="mmol/L" rawConc="0.000" rawConcUnit="mmol/L" sigCorr="0" sigCorrUnit="%"/>
         <REFERENCE source="NMR Database" unit="mmol/mol Crea" vmax="4400" vmin="-"/>
      </PARAMETER>
   </QUANTIFICATION>
</RESULTS>